README.rst
setup.py
MyAirthLib.egg-info/PKG-INFO
MyAirthLib.egg-info/SOURCES.txt
MyAirthLib.egg-info/dependency_links.txt
MyAirthLib.egg-info/requires.txt
MyAirthLib.egg-info/top_level.txt
appairth/__init__.py
appairth/module_add/__init__.py
appairth/module_add/controllers.py
appairth/module_add/models.py
appairth/templates/module_add/hello.html