Metadata-Version: 1.0
Name: MyAirthLib
Version: 0.1.7
Summary: This is demo arithmetic lib
Home-page: https://upload.pypi.org/legacy/MyAirthLib_v010/
Author: Shrawan shinde
Author-email: syntaxerror1972@gmail.com
License: MIT
Platform: UNKNOWN
